ats_resume_scorer/__init__.py
ats_resume_scorer/main.py
ats_resume_scorer/parsers/__init__.py
ats_resume_scorer/parsers/jd_parser.py
ats_resume_scorer/parsers/resume_parser.py
ats_resume_scorer/scoring/__init__.py
ats_resume_scorer/scoring/scoring_engine.py
ats_resume_scorer/utils/__init__.py
ats_resume_scorer/utils/report_generator.py
ats_resume_scorer-2.0.0.dist-info/licenses/LICENSE
ats_resume_scorer-2.0.0.dist-info/METADATA
ats_resume_scorer-2.0.0.dist-info/WHEEL
ats_resume_scorer-2.0.0.dist-info/entry_points.txt
ats_resume_scorer-2.0.0.dist-info/top_level.txt
ats_resume_scorer-2.0.0.dist-info/RECORD
