Metadata-Version: 2.4
Name: ats-resume-scorer
Version: 2.0.0
Summary: A comprehensive ATS Resume Scoring Plugin with advanced features including batch processing, web API, and Docker support
Home-page: https://github.com/yourusername/ats-resume-scorer
Author: Your Name
Author-email: Kumar Abhishek <developer@kabhishek18.com>
Maintainer-email: Kumar Abhishek <developer@kabhishek18.com>
License: MIT
Project-URL: Homepage, https://github.com/Kabhishek18/resume-ats-plugin
Project-URL: Documentation, https://github.com/Kabhishek18/resume-ats-plugin#readme
Project-URL: Repository, https://github.com/Kabhishek18/resume-ats-plugin.git
Project-URL: Bug Tracker, https://github.com/Kabhishek18/resume-ats-plugin/issues
Project-URL: Changelog, https://github.com/Kabhishek18/resume-ats-plugin/blob/main/CHANGELOG.md
Project-URL: Source Code, https://github.com/Kabhishek18/resume-ats-plugin
Project-URL: Download, https://pypi.org/project/ats-resume-scorer/
Project-URL: Funding, https://github.com/sponsors/kabhishek18
Keywords: ats,resume,scoring,hiring,recruitment,nlp,machine-learning,job-matching,cv-analysis,applicant-tracking,hr-tools,recruitment-automation
Classifier: Development Status :: 4 - Beta
Classifier: Intended Audience :: Developers
Classifier: Intended Audience :: End Users/Desktop
Classifier: License :: OSI Approved :: MIT License
Classifier: Operating System :: OS Independent
Classifier: Programming Language :: Python :: 3
Classifier: Programming Language :: Python :: 3.8
Classifier: Programming Language :: Python :: 3.9
Classifier: Programming Language :: Python :: 3.10
Classifier: Programming Language :: Python :: 3.11
Classifier: Programming Language :: Python :: 3.12
Classifier: Programming Language :: Python :: 3 :: Only
Classifier: Topic :: Software Development :: Libraries :: Python Modules
Classifier: Topic :: Text Processing :: Linguistic
Classifier: Topic :: Scientific/Engineering :: Artificial Intelligence
Classifier: Topic :: Scientific/Engineering :: Information Analysis
Classifier: Topic :: Office/Business
Classifier: Topic :: Utilities
Classifier: Environment :: Console
Classifier: Environment :: Web Environment
Classifier: Natural Language :: English
Classifier: Typing :: Typed
Requires-Python: >=3.8
License-File: LICENSE
Requires-Dist: spacy<4.0.0,>=3.4.0
Requires-Dist: PyMuPDF<2.0.0,>=1.20.0
Requires-Dist: python-docx<1.0.0,>=0.8.11
Requires-Dist: scikit-learn<2.0.0,>=1.1.0
Requires-Dist: numpy<2.0.0,>=1.21.0
Requires-Dist: pandas<3.0.0,>=1.3.0
Requires-Dist: PyPDF2<4.0.0,>=3.0.0
Provides-Extra: dev
Requires-Dist: pytest<8.0.0,>=7.0.0; extra == "dev"
Requires-Dist: pytest-cov<5.0.0,>=3.0.0; extra == "dev"
Requires-Dist: pytest-mock<4.0.0,>=3.6.0; extra == "dev"
Requires-Dist: black<24.0.0,>=22.0.0; extra == "dev"
Requires-Dist: flake8<7.0.0,>=4.0.0; extra == "dev"
Requires-Dist: mypy<2.0.0,>=0.950; extra == "dev"
Requires-Dist: pre-commit<4.0.0,>=2.17.0; extra == "dev"
Requires-Dist: bandit<2.0.0,>=1.7.0; extra == "dev"
Requires-Dist: safety<3.0.0,>=2.0.0; extra == "dev"
Requires-Dist: isort<6.0.0,>=5.10.0; extra == "dev"
Provides-Extra: web
Requires-Dist: fastapi<1.0.0,>=0.75.0; extra == "web"
Requires-Dist: uvicorn[standard]<1.0.0,>=0.17.0; extra == "web"
Requires-Dist: python-multipart<1.0.0,>=0.0.5; extra == "web"
Requires-Dist: jinja2<4.0.0,>=3.0.0; extra == "web"
Requires-Dist: python-jose[cryptography]<4.0.0,>=3.3.0; extra == "web"
Provides-Extra: docs
Requires-Dist: sphinx<7.0.0,>=4.5.0; extra == "docs"
Requires-Dist: sphinx-rtd-theme<2.0.0,>=1.0.0; extra == "docs"
Requires-Dist: myst-parser<1.0.0,>=0.17.0; extra == "docs"
Requires-Dist: sphinx-autodoc-typehints<2.0.0,>=1.17.0; extra == "docs"
Provides-Extra: monitoring
Requires-Dist: prometheus-client<1.0.0,>=0.14.0; extra == "monitoring"
Requires-Dist: psutil<6.0.0,>=5.8.0; extra == "monitoring"
Provides-Extra: database
Requires-Dist: psycopg2-binary<3.0.0,>=2.9.0; extra == "database"
Requires-Dist: redis<5.0.0,>=4.0.0; extra == "database"
Requires-Dist: sqlalchemy<3.0.0,>=1.4.0; extra == "database"
Requires-Dist: alembic<2.0.0,>=1.7.0; extra == "database"
Provides-Extra: all
Requires-Dist: ats-resume-scorer[database,dev,docs,monitoring,web]; extra == "all"
Dynamic: author
Dynamic: home-page
Dynamic: license-file
Dynamic: requires-python
